Metadata-Version: 2.1
Name: geometric
Version: 1.0.2
Summary: Geometry optimization for quantum chemistry
Home-page: https://github.com/leeping/geomeTRIC
Author: Lee-Ping Wang, Chenchen Song
Classifier: Development Status :: 5 - Production/Stable
Classifier: Intended Audience :: Science/Research
Classifier: Programming Language :: Python :: 2.7
Classifier: Programming Language :: Python :: 3
License-File: LICENSE
Requires-Dist: numpy>=1.11
Requires-Dist: networkx
Requires-Dist: six
